{
  "parent": "minecraft:recipes/root",
  "rewards": {
    "recipes": [
      "minecraft:mycelium_slab_from_mycelium_stonecutting"
    ]
  },
  "criteria": {
    "has_mycelium": {
      "trigger": "minecraft:inventory_changed",
      "conditions": {
        "items": [
          {
            "items": [
              "minecraft:mycelium"
            ]
          }
        ]
      }
    },
    "has_the_recipe": {
      "trigger": "minecraft:recipe_unlocked",
      "conditions": {
        "recipe": "minecraft:mycelium_slab_from_mycelium_stonecutting"
      }
    }
  },
  "requirements": [
    [
      "has_mycelium",
      "has_the_recipe"
    ]
  ]
}